{
  "__comment__": "This file was automatically created by mcresources",
  "type": "firmalife:mixing_bowl",
  "ingredients": [
    {
      "type": "tfc:not_rotten",
      "ingredient": {
        "item": "firmalife:food/vanilla_ice_cream"
      }
    },
    {
      "type": "tfc:not_rotten",
      "ingredient": {
        "item": "tfc:food/strawberry"
      }
    },
    {
      "type": "tfc:not_rotten",
      "ingredient": {
        "item": "tfc:food/strawberry"
      }
    }
  ],
  "output_item": {
    "item": "firmalife:food/strawberry_ice_cream"
  }
}